imgprocessing/__init__.py
imgprocessing/myfunctions.py
ndUtils-0.1.0.dist-info/METADATA
ndUtils-0.1.0.dist-info/WHEEL
ndUtils-0.1.0.dist-info/top_level.txt
ndUtils-0.1.0.dist-info/RECORD
